Metadata-Version: 2.1
Name: jani
Version: 0.1
Summary: This Scheduling Algorithm works on Data Frames
Home-page: https://github.com/harshjani53/schedulingAlgorithm
Download-URL: https://github.com/harshjani53/schedulingAlgorithm/archive/refs/tags/0.1.tar.gz
Author: HARSH JANI
Author-email: harshjani034699@gmail.com
License: MIT
License-File: LICENSE.txt
